aperol/__init__.py
aperol/config.py
aperol/tree_utils.py
aperol-0.0.0a0.dist-info/LICENSE
aperol-0.0.0a0.dist-info/METADATA
aperol-0.0.0a0.dist-info/WHEEL
aperol-0.0.0a0.dist-info/top_level.txt
aperol-0.0.0a0.dist-info/RECORD
