Metadata-Version: 2.1
Name: aperol
Version: 0.0.0a0
Summary: Aperol: A featherweight framework for configuration of Python objects
Author-email: Ryan Eloff <ryaneloff@gmail.com>
License: Apache-2.0
Project-URL: Homepage, https://github.com/rpeloff/aperol
Project-URL: Repository, https://github.com/rpeloff/aperol.git
Keywords: aperol,config,configuration,machine,learning
Classifier: Programming Language :: Python :: 3.10
Classifier: Programming Language :: Python :: 3.11
Classifier: Programming Language :: Python :: 3.12
Classifier: License :: OSI Approved :: Apache Software License
Requires-Python: >=3.10
License-File: LICENSE
Requires-Dist: pyyaml
